pyjarowinkler/__init__.py
pyjarowinkler/comparative.py
pyjarowinkler/distance.py
pyjarowinkler/glyph.py
pyjarowinkler-3.0.0.dist-info/WHEEL
pyjarowinkler-3.0.0.dist-info/METADATA
pyjarowinkler-3.0.0.dist-info/RECORD
