Metadata-Version: 2.3
Name: pyjarowinkler
Version: 3.0.0
Summary: Finds the Jaro Winkler Distance indicating a distance or similarity score between two strings.
Keywords: delta,diff,distance,similarity,jaro,score,string,winkler
Author: Jean-Bernard Ratte
Author-email: Jean-Bernard Ratte <jean.bernard.ratte@unary.ca>
License:                                  Apache License
Classifier: Development Status :: 5 - Production/Stable
Classifier: Intended Audience :: Developers
Classifier: Intended Audience :: Science/Research
Classifier: License :: OSI Approved :: Apache Software License
Classifier: Operating System :: OS Independent
Classifier: Programming Language :: Python
Classifier: Programming Language :: Python :: 3
Classifier: Programming Language :: Python :: 3.10
Classifier: Programming Language :: Python :: 3.11
Classifier: Programming Language :: Python :: 3.12
Classifier: Programming Language :: Python :: 3.13
Classifier: Programming Language :: Python :: 3.14
Classifier: Topic :: Text Processing
Requires-Dist: mypy ; extra == 'dev'
Requires-Dist: ruff ; extra == 'dev'
Requires-Dist: coverage ; extra == 'dev'
Requires-Dist: coverage[toml] ; extra == 'dev'
Maintainer: Jean-Bernard Ratte
Maintainer-email: Jean-Bernard Ratte <jean.bernard.ratte@unary.ca>
Requires-Python: >=3.10
Project-URL: Documentation, https://github.com/nap/jaro-winkler-distance#readme
Project-URL: Homepage, https://pypi.org/project/pyjarowinkler/
Project-URL: Issues, https://github.com/nap/jaro-winkler-distance/issues
Project-URL: Repository, https://github.com/nap/jaro-winkler-distance.git
Project-URL: Source, https://github.com/nap/jaro-winkler-distance
Provides-Extra: dev
